iranian/__init__.py
iranian/iran.py
yazd-0.1.0.dist-info/LICENSE
yazd-0.1.0.dist-info/METADATA
yazd-0.1.0.dist-info/WHEEL
yazd-0.1.0.dist-info/top_level.txt
yazd-0.1.0.dist-info/RECORD
