Metadata-Version: 2.1
Name: yazd
Version: 0.1.0
Summary: This is Iran
Author: Z3N
Author-email: iliya.souri7890@example.com
Classifier: Programming Language :: Python :: 3
Classifier: License :: OSI Approved :: MIT License
Classifier: Operating System :: OS Independent
Requires-Python: >=3.7
License-File: LICENSE
